quantaq_cli/__init__.py
quantaq_cli/console/__init__.py
quantaq_cli/console/commands/__init__.py
quantaq_cli/console/commands/concat.py
quantaq_cli/console/commands/expunge.py
quantaq_cli/console/commands/flag.py
quantaq_cli/console/commands/merge.py
quantaq_cli/console/commands/munge.py
quantaq_cli/console/commands/resample.py
quantaq_cli/exceptions.py
quantaq_cli/utilities.py
quantaq_cli/variables.py
quantaq_cli-0.5.0.dist-info/entry_points.txt
quantaq_cli-0.5.0.dist-info/LICENSE
quantaq_cli-0.5.0.dist-info/WHEEL
quantaq_cli-0.5.0.dist-info/METADATA
quantaq_cli-0.5.0.dist-info/RECORD
