Metadata-Version: 2.1
Name: quantaq-cli
Version: 0.5.0
Summary: The QuantAQ CLI
Home-page: https://github.com/quant-aq/cli
License: Apache-2.0
Author: David H Hagan
Author-email: david.hagan@quant-aq.com
Requires-Python: >=3.8,<4
Classifier: License :: OSI Approved :: Apache Software License
Classifier: Programming Language :: Python :: 3
Classifier: Programming Language :: Python :: 3.8
Classifier: Programming Language :: Python :: 3.9
Classifier: Programming Language :: Python :: 3.10
Classifier: Programming Language :: Python :: 3.11
Requires-Dist: click (>=7.1.2,<8.0.0)
Requires-Dist: numpy (>=1.23.2,<2.0.0)
Requires-Dist: pandas (>=1.0.4)
Requires-Dist: pyarrow (>=0.17.1)
Requires-Dist: rich-click (>=1.5.2,<2.0.0)
Requires-Dist: terminaltables (>=3.1.0,<4.0.0)
Requires-Dist: urllib3 (>=1.26.10,<2.0.0)
Project-URL: Repository, https://github.com/quant-aq/cli
